datashredder/__init__.py
datashredder/corrupt.py
datashredder/random_corrupt.py
datashredder/swap_corrupt.py
Datashredder-0.2.21.dist-info/LICENSE
Datashredder-0.2.21.dist-info/METADATA
Datashredder-0.2.21.dist-info/WHEEL
Datashredder-0.2.21.dist-info/top_level.txt
Datashredder-0.2.21.dist-info/RECORD
