Metadata-Version: 2.1
Name: Datashredder
Version: 0.2.21
Summary: A simple data corruption engine written in python
Home-page: https://github.com/awesomelewis2007/Datashredder/
Author: Lewis Evans
Author-email: awesomelewis2007@gmail.com
License: GNU
Platform: UNKNOWN
License-File: LICENSE
